madcc/__init__.py
madcc/entrypoints/__init__.py
madcc/entrypoints/crypto_assets.py
madcc/entrypoints/kraken_limits.py
madcc/kraken/__init__.py
madcc/kraken/kraken.py
madcc/utils/__init__.py
madcc/utils/crypto_assets.py
madcc-0.1.3.dist-info/METADATA
madcc-0.1.3.dist-info/RECORD
madcc-0.1.3.dist-info/WHEEL
madcc-0.1.3.dist-info/entry_points.txt
madcc-0.1.3.dist-info/top_level.txt
