Metadata-Version: 2.1
Name: madcc
Version: 0.1.3
Summary: madtech cryptocurrency functions
Home-page: https://github.com/madeddie/madcc
Author: Edwin Hermans
Author-email: edwin@madtech.cx
License: MIT
Keywords: personal project cryptocurrency kraken gdax coinmarketcap
Platform: UNKNOWN
Classifier: Development Status :: 4 - Beta
Classifier: Intended Audience :: Developers
Classifier: Topic :: Utilities
Classifier: License :: OSI Approved :: MIT License
Classifier: Programming Language :: Python :: 3
Classifier: Programming Language :: Python :: 3.4
Classifier: Programming Language :: Python :: 3.5
Classifier: Programming Language :: Python :: 3.6
Classifier: Programming Language :: Python :: 3.7
Requires-Python: ~=3.4
Requires-Dist: clint
Requires-Dist: coinmarketcap
Requires-Dist: krakenex
Requires-Dist: requests
Requires-Dist: tabulate
